xrandom/__init__.py
xrandom/xrandom.py
xrandom-0.1.5.dist-info/LICENSE
xrandom-0.1.5.dist-info/METADATA
xrandom-0.1.5.dist-info/WHEEL
xrandom-0.1.5.dist-info/top_level.txt
xrandom-0.1.5.dist-info/RECORD
